[
    {
        "moduleName": "public",
        "name": "companiesAdmin",
        "En": "Administration Permissions",
        "Ar": "َصلاحيات الإدارة",
        "permissions": [
            "securityManage",
            "numberingManage",
            "systemSettingManage",
            "printersPathsManage",
            "attendanceLeavingManage",
            "countriesManage",
            "journalEntryManage",
            "generalLedgerManage",
            "assistantGeneralLedgerManage",
            "costCentersManage",
            "accountsGuideManage",
            "budgetClassificationsManage",
            "incomeListManage",
            "activeSubstancesManage",
            "citiesManage",
            "currenciesManage",
            "jobsShiftsManage",
            "discountTypesManage",
            "doctorDeskTopManage",
            "namesConversionsManage",
            "purchaseRequestsManage",
            "itemsGroupManage",
            "safesManage",
            "storesItemsManage",
            "taxesTypesManage",
            "vendorsManage",
            "vendorsGroupManage",
            "storesUnitsManage",
            "govesManage",
            "areasManage",
            "nationalitiesManage",
            "departmentsManage",
            "sectionsManage",
            "employeesBonusNamesManage",
            "employeesPenaltiesNamesManage",
            "jobsManage",
            "doctorAppointmentsManage",
            "laboratoryDeskTopManage",
            "radiologyDeskTopManage",
            "employeesManage",
            "employeesBonusesManage",
            "employeesPenaltiesManage",
            "salaryDeductionsNamesManage",
            "salaryAllowancesNamesManage",
            "jobsToolsManage",
            "servicesManage",
            "servicesGroupsManage",
            "servicesCategoriesManage",
            "servicesOrdersManage",
            "achiCodesManage",
            "medicalOffersManage",
            "patientsManage",
            "insuranceCompaniesManage",
            "insuranceContractsManage",
            "mainInsuranceCompaniesManage",
            "hospitalResponsibilitiesManage",
            "doctorsManage",
            "specialtiesManage",
            "storesManage",
            "chiefComplaintsManage",
            "medicinesManage",
            "significantSignsManage",
            "patientRecommendationsManage",
            "patientEducationsManage",
            "patientsApprovalManage",
            "otherConditionsManage",
            "medicineDurationsManage",
            "medicineFrequenciesManage",
            "medicineRoutesManage",
            "patientHistoryManage",
            "diagnosesManage",
            "drinksManage",
            "foodsManage",
            "insuranceClassesManage",
            "convertUnitsManage",
            "customersManage",
            "customersGroupsManage",
            "damageItemsManage",
            "itemsGroupsManage",
            "purchaseOrdersManage",
            "returnPurchaseOrdersManage",
            "returnSalesInvoicesManage",
            "salesInvoicesManage",
            "salesCompaniesInvoicesManage",
            "salesPatientsInvoicesManage",
            "storesItemsCardManage",
            "transferItemsOrdersManage",
            "transferItemsRequestsManage",
            "vendorsGroupsManage",
            "reasonsDestroyingItemsManage",
            "storesOpeningBalancesManage",
            "stockTakingManage",
            "vacationsRequestsManage",
            "vacationsTypesManage",
            "createVacationsManage",
            "vacationsNamesManage",
            "banksManage",
            "delayRequestsManage",
            "workErrandRequestsManage",
            "overtimeRequestsManage",
            "employeesAdvancesManage",
            "payslipsManage",
            "jobsAdvertisementsManage",
            "jobsApplicantsManage",
            "employeesContractsManage"
        ]
    }
]
